Workbook

Sheet Câu hỏi 3 ngôn ngữ
A1: Mã | B1: Nhóm | C1: Công cụ mong đợi | D1: Câu hỏi — Tiếng Việt | E1: Question — English | F1: ຄຳຖາມ — ພາສາລາວ | G1: Cần thấy gì trong câu trả lời | H1: Kết quả | I1: Ghi chú
A2: A1 | B2: Tổng quan | C2: tong_quan_hom_nay | D2: Hôm nay có gì cần lo không? | E2: Anything I should worry about today? | F2: ມື້ນີ້ມີຫຍັງຕ້ອງກັງວົນບໍ? | G2: Nêu được sự cố đang mở, lệnh quá hạn/gần trễ, xe và tài xế rảnh, giấy tờ sắp hết hạn. | H2: Chưa thử
A3: A2 | B3: Tổng quan | C3: tong_quan_hom_nay | D3: Tóm tắt tình hình vận hành hôm nay cho anh. | E3: Give me a summary of today's operations. | F3: ສະຫຼຸບສະພາບການດຳເນີນງານມື້ນີ້ໃຫ້ແດ່. | G3: Một đoạn ngắn có số liệu, không dài dòng, có mã lệnh để tra lại. | H3: Chưa thử
A4: A3 | B4: Tổng quan | C4: tong_quan_hom_nay · phan_tich_lenh_giao_hang | D4: Có bao nhiêu lệnh giao hàng đang chạy và bao nhiêu đã hoàn tất? | E4: How many delivery orders are in transit and how many are completed? | F4: ມີ DO ຈັກໃບກຳລັງຂົນສົ່ງ ແລະ ຈັກໃບສຳເລັດແລ້ວ? | G4: Hai con số khớp ĐÚNG ô 'Đang vận chuyển' và 'Hoàn thành' trên bảng Phân tích lệnh giao hàng. Đây là câu bẫy: đếm thô theo trạng thái sẽ ra số khác (gộp cả lệnh đã tới chờ ký). | H4: Chưa thử
A5: A4 | B5: Tổng quan | C5: tong_quan_hom_nay | D5: Việc gì gấp nhất bây giờ? | E5: What is the most urgent thing right now? | F5: ຫຍັງດ່ວນທີ່ສຸດຕອນນີ້? | G5: Chọn ra được việc gấp (quá hạn / sự cố High) chứ không liệt kê lại tất cả. | H5: Chưa thử
A6: A5 | B6: Tổng quan | C6: su_co · nguon_luc_doi_xe | D6: Hôm nay có hư hỏng gì không? | E6: Any breakdowns today? | F6: ມື້ນີ້ມີການເສຍຫາຍຫຍັງບໍ? | G6: Nêu sự cố loại hỏng hóc/hàng hư hỏng kèm xe và mã lệnh. | H6: Chưa thử
A7: B1 | B7: Lệnh giao hàng | C7: phan_tich_lenh_giao_hang · lenh_giao_hang | D7: Có lệnh nào quá hạn không, của khách nào? | E7: Are any orders overdue, and for which customer? | F7: ມີ DO ໃດເກີນກຳນົດບໍ, ຂອງລູກຄ້າໃດ? | G7: Đúng mã lệnh VÀ đúng tên khách (số ngày 12/09 là 2 lệnh DO-2026-0026, khách Samsung Electronics HCMC CE — dữ liệu làm tươi mỗi buổi, hãy đối chiếu màn hình). Tên khách sai là LỖI NẶNG — xem mục 6.2 của tài liệu. | H7: Chưa thử
A8: B2 | B8: Lệnh giao hàng | C8: phan_tich_lenh_giao_hang | D8: Lệnh nào sắp trễ trong 24 giờ tới? | E8: Which orders are about to be late within the next 24 hours? | F8: DO ໃດໃກ້ຊ້າພາຍໃນ 24 ຊົ່ວໂມງ? | G8: Nhóm Gần trễ, kèm mã lệnh và hạn giao (số ngày 12/09 là 1 lệnh — dữ liệu làm tươi mỗi buổi, hãy đối chiếu màn hình). | H8: Chưa thử
A9: B3 | B9: Lệnh giao hàng | C9: phan_tich_lenh_giao_hang | D9: Còn bao nhiêu lệnh chờ điều phối xe? | E9: How many orders are still waiting for a vehicle? | F9: ຍັງມີ DO ຈັກໃບລໍຖ້າຈັດລົດ? | G9: Con số khớp ĐÚNG ô 'Chờ vận chuyển' trên bảng. Bẫy: đếm thô trạng thái pending sẽ cao hơn, vì bảng đã tách các lệnh quá hạn và gần trễ ra khỏi ô này. | H9: Chưa thử
A10: B4 | B10: Lệnh giao hàng | C10: theo_doi_lenh | D10: Cho anh xem chi tiết lệnh DO-2026-0050-DO01. | E10: Show me the details of order DO-2026-0050-DO01. | F10: ຂໍເບິ່ງລາຍລະອຽດ DO-2026-0050-DO01. | G10: Khách Vinamilk, tuyến Sóng Thần → Cảng Cát Lái, giá 1.406.000 VNĐ, xe DEMO-61H-888.02. | H10: Chưa thử
A11: B5 | B11: Lệnh giao hàng | C11: theo_doi_lenh | D11: Lệnh DO-2026-0050-DO01 đang ở đâu, bao giờ tới? | E11: Where is order DO-2026-0050-DO01 now, and when will it arrive? | F11: DO-2026-0050-DO01 ຢູ່ໃສແລ້ວ, ຈະຮອດເມື່ອໃດ? | G11: Trạng thái đang vận chuyển, mốc kế tiếp, và nói rõ GPS là vị trí mô phỏng nếu đúng vậy. | H11: Chưa thử
A12: B6 | B12: Lệnh giao hàng | C12: lenh_giao_hang | D12: Những lệnh nào chưa có xe và tài xế? | E12: Which orders have no vehicle and driver assigned yet? | F12: DO ໃດຍັງບໍ່ມີລົດ ແລະ ຄົນຂັບ? | G12: Danh sách lệnh trạng thái chờ điều phối, không lẫn lệnh đã có xe. | H12: Chưa thử
A13: B7 | B13: Lệnh giao hàng | C13: lenh_giao_hang | D13: Lệnh giao hàng của Vinamilk có những cái nào? | E13: Which delivery orders belong to Vinamilk? | F13: DO ໃດແດ່ເປັນຂອງ Vinamilk? | G13: Tìm được theo TÊN khách (không phải mã khách), kèm trạng thái từng lệnh. | H13: Chưa thử
... A74: L4 | B74: Định dạng | C74: chuyen_dang_chay | D74: Liệt kê 5 chuyến đang chạy dạng bảng, có tài xế và khách. | E74: List 5 running trips as a table, with driver and customer. | F74: ລາຍການ 5 ຖ້ຽວທີ່ກຳລັງແລ່ນເປັນຕາຕະລາງ, ມີຄົນຂັບ ແລະ ລູກຄ້າ. | G74: Ra bảng Markdown hiển thị đúng trên trang, cột số căn phải. | H74: Chưa thử

Sheet Kịch bản theo bước
A1: Mã | B1: Nhóm | C1: Bước | D1: Cách làm | E1: Kết quả mong đợi | F1: Kết quả | G1: Ghi chú
A2: S1 | B2: Chuẩn bị | C2: Kiểm máy chủ EPL đã host | D2: Mở http://senvangsolutions.com:1506/api/health — trợ lý mặc định hỏi máy chủ này, không cần bật gì trên máy mình | E2: Trả về {"status":"ok"}. Nếu không mở được thì kiểm đường mạng trước khi làm tiếp. | F2: Chưa thử
A3: S2 | B3: Chuẩn bị | C3: Bật máy chủ trợ lý | D3: Ở D:\Demo_Lao\EPL_TroLy bấm đúp chay.bat (hoặc: python chay.py) | E3: Cửa sổ hiện: Trang http://localhost:8090 · API EPL có token · Gemini có khóa · Công cụ 21 · Giám sát mỗi 15 giây. | F3: Chưa thử
A4: S3 | B4: Chuẩn bị | C4: Kiểm sức khoẻ | D4: Mở http://localhost:8090/suc-khoe | E4: gemini_co_khoa: true · epl_ok: true · so_cong_cu: 21. Nếu epl_ok false thì máy chủ EPL chưa bật. | F4: Chưa thử
A5: S4 | B5: Giao diện | C5: Mở trang, nhìn màn chào | D5: Mở http://localhost:8090 | E5: Logo EPL, lời chào theo buổi, 6 gợi ý câu hỏi, ô nhập ở giữa. KHÔNG có dải đỏ báo lỗi ở đầu trang. | F5: Chưa thử
A6: S5 | B6: Giao diện | C6: Đổi ba ngôn ngữ | D6: Bấm lần lượt Tiếng Việt · English · ລາວ ở góc dưới trái | E6: Toàn bộ nhãn, lời chào và 6 gợi ý đổi theo. Chữ Lào hiện đúng dấu, không ô vuông. | F6: Chưa thử
A7: S6 | B7: Giao diện | C7: Đổi sáng/tối | D7: Bấm 'Giao diện' ở góc dưới trái | E7: Nền đổi sáng ↔ tối, chữ vẫn đọc được, ghi nhớ khi tải lại trang. | F7: Chưa thử
A8: S7 | B8: Giao diện | C8: Trò chuyện mới và lịch sử | D8: Hỏi 1 câu → bấm 'Trò chuyện mới' → hỏi câu khác → bấm lại cuộc cũ ở thanh bên | E8: Hai cuộc nằm riêng ở thanh bên; mở lại cuộc cũ thấy nguyên nội dung. Tải lại trang (F5) vẫn còn. | F8: Chưa thử
A9: S8 | B9: Giao diện | C9: Xoá một cuộc | D9: Rê chuột lên một cuộc trong thanh bên, bấm dấu × | E9: Cuộc đó biến mất, các cuộc khác giữ nguyên. | F9: Chưa thử
A10: S9 | B10: Tốc độ | C10: Xem stream khi hỏi | D10: Hỏi câu A1 và nhìn đồng hồ | E10: Trong ~2 giây hiện chip 'Đang tra: Tổng quan hôm nay'; chữ bắt đầu chảy trước giây thứ 5; xong trong khoảng 5–9 giây. Không ngồi nhìn ba chấm suốt. | F10: Chưa thử
A11: S10 | B11: Tốc độ | C11: Câu nối tiếp nhanh hơn | D11: Hỏi tiếp J1 ngay sau A1 | E11: Xong trong ~2–3 giây và KHÔNG có chip công cụ nào. | F11: Chưa thử
A12: S11 | B12: Thông báo | C12: Chuông khi có báo giá mới | D12: Mở màn Báo giá của hệ EPL, tạo một báo giá nháp mới | E12: Trong vòng ~15 giây: chuông góc phải hiện số, một toast trượt ra ghi 'Báo giá mới QT-… cho <khách> · giá …'. | F12: Chưa thử
A13: S12 | B13: Thông báo | C13: Chuông khi có lệnh mới | D13: Trên hệ EPL, cho khách chấp nhận một báo giá (sinh DO tự động) | E13: Thông báo 'Lệnh giao hàng mới DO-… cho <khách>'. | F13: Chưa thử
... A22: S21 | B22: Điện thoại | C22: Mở trên điện thoại | D22: Trên điện thoại cùng Wi-Fi, mở http://<IP máy>:8090 | E22: Thanh bên thu vào, có nút ☰ để mở; ô nhập và chuông vẫn bấm được; chữ không tràn ngang. | F22: Chưa thử

Sheet Tổng hợp
A1: Nhóm câu hỏi | B1: Tổng câu | C1: Đạt | D1: Không đạt | E1: Chưa thử | F1: Tỉ lệ đạt
A2: Tổng quan | B2: =COUNTIF('Câu hỏi 3 ngôn ngữ'!$B$2:$B$74,A2) | C2: =COUNTIFS('Câu hỏi 3 ngôn ngữ'!$B$2:$B$74,A2,'Câu hỏi 3 ngôn ngữ'!$H$2:$H$74,"Đạt") | D2: =COUNTIFS('Câu hỏi 3 ngôn ngữ'!$B$2:$B$74,A2,'Câu hỏi 3 ngôn ngữ'!$H$2:$H$74,"Không đạt") | E2: =COUNTIFS('Câu hỏi 3 ngôn ngữ'!$B$2:$B$74,A2,'Câu hỏi 3 ngôn ngữ'!$H$2:$H$74,"Chưa thử") | F2: =IF(B2=0,"",C2/B2)
A3: Lệnh giao hàng | B3: =COUNTIF('Câu hỏi 3 ngôn ngữ'!$B$2:$B$74,A3) | C3: =COUNTIFS('Câu hỏi 3 ngôn ngữ'!$B$2:$B$74,A3,'Câu hỏi 3 ngôn ngữ'!$H$2:$H$74,"Đạt") | D3: =COUNTIFS('Câu hỏi 3 ngôn ngữ'!$B$2:$B$74,A3,'Câu hỏi 3 ngôn ngữ'!$H$2:$H$74,"Không đạt") | E3: =COUNTIFS('Câu hỏi 3 ngôn ngữ'!$B$2:$B$74,A3,'Câu hỏi 3 ngôn ngữ'!$H$2:$H$74,"Chưa thử") | F3: =IF(B3=0,"",C3/B3)
A4: Chuyến | B4: =COUNTIF('Câu hỏi 3 ngôn ngữ'!$B$2:$B$74,A4) | C4: =COUNTIFS('Câu hỏi 3 ngôn ngữ'!$B$2:$B$74,A4,'Câu hỏi 3 ngôn ngữ'!$H$2:$H$74,"Đạt") | D4: =COUNTIFS('Câu hỏi 3 ngôn ngữ'!$B$2:$B$74,A4,'Câu hỏi 3 ngôn ngữ'!$H$2:$H$74,"Không đạt") | E4: =COUNTIFS('Câu hỏi 3 ngôn ngữ'!$B$2:$B$74,A4,'Câu hỏi 3 ngôn ngữ'!$H$2:$H$74,"Chưa thử") | F4: =IF(B4=0,"",C4/B4)
A5: Sự cố | B5: =COUNTIF('Câu hỏi 3 ngôn ngữ'!$B$2:$B$74,A5) | C5: =COUNTIFS('Câu hỏi 3 ngôn ngữ'!$B$2:$B$74,A5,'Câu hỏi 3 ngôn ngữ'!$H$2:$H$74,"Đạt") | D5: =COUNTIFS('Câu hỏi 3 ngôn ngữ'!$B$2:$B$74,A5,'Câu hỏi 3 ngôn ngữ'!$H$2:$H$74,"Không đạt") | E5: =COUNTIFS('Câu hỏi 3 ngôn ngữ'!$B$2:$B$74,A5,'Câu hỏi 3 ngôn ngữ'!$H$2:$H$74,"Chưa thử") | F5: =IF(B5=0,"",C5/B5)
A6: Báo giá | B6: =COUNTIF('Câu hỏi 3 ngôn ngữ'!$B$2:$B$74,A6) | C6: =COUNTIFS('Câu hỏi 3 ngôn ngữ'!$B$2:$B$74,A6,'Câu hỏi 3 ngôn ngữ'!$H$2:$H$74,"Đạt") | D6: =COUNTIFS('Câu hỏi 3 ngôn ngữ'!$B$2:$B$74,A6,'Câu hỏi 3 ngôn ngữ'!$H$2:$H$74,"Không đạt") | E6: =COUNTIFS('Câu hỏi 3 ngôn ngữ'!$B$2:$B$74,A6,'Câu hỏi 3 ngôn ngữ'!$H$2:$H$74,"Chưa thử") | F6: =IF(B6=0,"",C6/B6)
A7: Cơ hội | B7: =COUNTIF('Câu hỏi 3 ngôn ngữ'!$B$2:$B$74,A7) | C7: =COUNTIFS('Câu hỏi 3 ngôn ngữ'!$B$2:$B$74,A7,'Câu hỏi 3 ngôn ngữ'!$H$2:$H$74,"Đạt") | D7: =COUNTIFS('Câu hỏi 3 ngôn ngữ'!$B$2:$B$74,A7,'Câu hỏi 3 ngôn ngữ'!$H$2:$H$74,"Không đạt") | E7: =COUNTIFS('Câu hỏi 3 ngôn ngữ'!$B$2:$B$74,A7,'Câu hỏi 3 ngôn ngữ'!$H$2:$H$74,"Chưa thử") | F7: =IF(B7=0,"",C7/B7)
A8: Khách hàng | B8: =COUNTIF('Câu hỏi 3 ngôn ngữ'!$B$2:$B$74,A8) | C8: =COUNTIFS('Câu hỏi 3 ngôn ngữ'!$B$2:$B$74,A8,'Câu hỏi 3 ngôn ngữ'!$H$2:$H$74,"Đạt") | D8: =COUNTIFS('Câu hỏi 3 ngôn ngữ'!$B$2:$B$74,A8,'Câu hỏi 3 ngôn ngữ'!$H$2:$H$74,"Không đạt") | E8: =COUNTIFS('Câu hỏi 3 ngôn ngữ'!$B$2:$B$74,A8,'Câu hỏi 3 ngôn ngữ'!$H$2:$H$74,"Chưa thử") | F8: =IF(B8=0,"",C8/B8)
A9: Đội xe | B9: =COUNTIF('Câu hỏi 3 ngôn ngữ'!$B$2:$B$74,A9) | C9: =COUNTIFS('Câu hỏi 3 ngôn ngữ'!$B$2:$B$74,A9,'Câu hỏi 3 ngôn ngữ'!$H$2:$H$74,"Đạt") | D9: =COUNTIFS('Câu hỏi 3 ngôn ngữ'!$B$2:$B$74,A9,'Câu hỏi 3 ngôn ngữ'!$H$2:$H$74,"Không đạt") | E9: =COUNTIFS('Câu hỏi 3 ngôn ngữ'!$B$2:$B$74,A9,'Câu hỏi 3 ngôn ngữ'!$H$2:$H$74,"Chưa thử") | F9: =IF(B9=0,"",C9/B9)
A10: Tài xế | B10: =COUNTIF('Câu hỏi 3 ngôn ngữ'!$B$2:$B$74,A10) | C10: =COUNTIFS('Câu hỏi 3 ngôn ngữ'!$B$2:$B$74,A10,'Câu hỏi 3 ngôn ngữ'!$H$2:$H$74,"Đạt") | D10: =COUNTIFS('Câu hỏi 3 ngôn ngữ'!$B$2:$B$74,A10,'Câu hỏi 3 ngôn ngữ'!$H$2:$H$74,"Không đạt") | E10: =COUNTIFS('Câu hỏi 3 ngôn ngữ'!$B$2:$B$74,A10,'Câu hỏi 3 ngôn ngữ'!$H$2:$H$74,"Chưa thử") | F10: =IF(B10=0,"",C10/B10)
A11: Tuyến | B11: =COUNTIF('Câu hỏi 3 ngôn ngữ'!$B$2:$B$74,A11) | C11: =COUNTIFS('Câu hỏi 3 ngôn ngữ'!$B$2:$B$74,A11,'Câu hỏi 3 ngôn ngữ'!$H$2:$H$74,"Đạt") | D11: =COUNTIFS('Câu hỏi 3 ngôn ngữ'!$B$2:$B$74,A11,'Câu hỏi 3 ngôn ngữ'!$H$2:$H$74,"Không đạt") | E11: =COUNTIFS('Câu hỏi 3 ngôn ngữ'!$B$2:$B$74,A11,'Câu hỏi 3 ngôn ngữ'!$H$2:$H$74,"Chưa thử") | F11: =IF(B11=0,"",C11/B11)
A12: Tỷ giá | B12: =COUNTIF('Câu hỏi 3 ngôn ngữ'!$B$2:$B$74,A12) | C12: =COUNTIFS('Câu hỏi 3 ngôn ngữ'!$B$2:$B$74,A12,'Câu hỏi 3 ngôn ngữ'!$H$2:$H$74,"Đạt") | D12: =COUNTIFS('Câu hỏi 3 ngôn ngữ'!$B$2:$B$74,A12,'Câu hỏi 3 ngôn ngữ'!$H$2:$H$74,"Không đạt") | E12: =COUNTIFS('Câu hỏi 3 ngôn ngữ'!$B$2:$B$74,A12,'Câu hỏi 3 ngôn ngữ'!$H$2:$H$74,"Chưa thử") | F12: =IF(B12=0,"",C12/B12)
A13: Doanh thu | B13: =COUNTIF('Câu hỏi 3 ngôn ngữ'!$B$2:$B$74,A13) | C13: =COUNTIFS('Câu hỏi 3 ngôn ngữ'!$B$2:$B$74,A13,'Câu hỏi 3 ngôn ngữ'!$H$2:$H$74,"Đạt") | D13: =COUNTIFS('Câu hỏi 3 ngôn ngữ'!$B$2:$B$74,A13,'Câu hỏi 3 ngôn ngữ'!$H$2:$H$74,"Không đạt") | E13: =COUNTIFS('Câu hỏi 3 ngôn ngữ'!$B$2:$B$74,A13,'Câu hỏi 3 ngôn ngữ'!$H$2:$H$74,"Chưa thử") | F13: =IF(B13=0,"",C13/B13)
... A19: Định dạng | B19: =COUNTIF('Câu hỏi 3 ngôn ngữ'!$B$2:$B$74,A19) | C19: =COUNTIFS('Câu hỏi 3 ngôn ngữ'!$B$2:$B$74,A19,'Câu hỏi 3 ngôn ngữ'!$H$2:$H$74,"Đạt") | D19: =COUNTIFS('Câu hỏi 3 ngôn ngữ'!$B$2:$B$74,A19,'Câu hỏi 3 ngôn ngữ'!$H$2:$H$74,"Không đạt") | E19: =COUNTIFS('Câu hỏi 3 ngôn ngữ'!$B$2:$B$74,A19,'Câu hỏi 3 ngôn ngữ'!$H$2:$H$74,"Chưa thử") | F19: =IF(B19=0,"",C19/B19)
A20: TỔNG CỘNG | B20: =SUM(B2:B19) | C20: =SUM(C2:C19) | D20: =SUM(D2:D19) | E20: =SUM(E2:E19) | F20: =IF(B20=0,"",C20/B20)
A22: Điều kiện bắt buộc để coi là xong: nhóm Ranh giới phải đạt 100%. Nhóm này kiểm trợ lý KHÔNG làm nghiệp vụ.

Sheet Số liệu tham chiếu
A1: Mục | B1: Giá trị tại 12/09/2026
A2: Khách hàng | B2: 15
A3: Tuyến đường | B3: 8
A4: Xe | B4: 12
A5: Tài xế | B5: 16
A6: Loại phương tiện | B6: 6
A7: Tiền tệ | B7: 4 (VNĐ, USD 26.173,5, THB 710, LAK 1,18)
A8: DO đang vận chuyển | B8: 11
A9: DO đã hoàn tất | B9: 21
A10: DO chờ điều phối | B10: 13
A11: DO quá hạn | B11: 2 — DO-2026-0026-DO01/DO02, khách Samsung Electronics HCMC CE
A12: DO gần trễ (24h) | B12: 1
... A21: Bộ dữ liệu demo tài xế | B21: Somsak Phommachanh (DEMO-DRV-015) · xe DEMO-61H-888.02 · chuyến TRIP-TAIXE-DEMO-01 chở DO-2026-0050-DO01 (Vinamilk) và DO-2026-0051-DO01 (Acecook), mỗi lệnh 1.406.000 VNĐ
A23: Dữ liệu thay đổi theo thời gian. Dùng bảng này để biết thứ tự độ lớn có đúng không; con số chính xác thì đối chiếu màn hình gốc.
